{
  "license": [
    {
      "user": "6283138114398",
      "bot": [
        "6288994448564",
        "6285141620081"
      ],
      "token": "MallzDev",
      "limit": 999
    },
    {
      "user": "6281549236243",
      "bot": [
        "6281549236243"
      ],
      "token": "jagpro_manzjwkksj82jsk27",
      "limit": 1
    },
    {
      "user": "6285923467853",
      "bot": [
        "6283851150463"
      ],
      "token": "jagpro_skprjkskyblankgsh892",
      "limit": 1
    },
    {
      "user": "62811147526",
      "bot": [
        "6285162828539"
      ],
      "token": "jagpro_skpjuebeufqqjs69003",
      "limit": 1
    },
    {
      "user": "6285178399532",
      "bot": [
        "628999809547"
      ],
      "token": "RafkaVL",
      "limit": 1
    },
    {
      "user": "6281325503645",
      "bot": [
        "6281325507265"
      ],
      "token": "jagpro_skpjgsjhhebbsjtq827",
      "limit": 1
    },
    {
      "user": "6285363276961",
      "bot": [
        "6285126539345"
      ],
      "token": "kyybotzV2",
      "limit": 1
    },
    {
      "user": "6289525459709",
      "bot": [
        "6285136558181"
      ],
      "token": "danimaru",
      "limit": 1
    },
    {
      "user": "6282211426930",
      "bot": [
        "6282211426930"
      ],
      "token": "jagpro_khtkof4hwxpgeta2",
      "limit": 1
    },
    {
      "user": "31687593822",
      "bot": [
        "6285196253851"
      ],
      "token": "jagpro_zgcyntq2y7y1rx4g",
      "limit": 1
    },
    {
      "user": "6285167292908",
      "bot": [
        "6285167292908"
      ],
      "token": "jagpro_jglg2v1t8a7uo73q",
      "limit": 1
    },
    {
      "user": "6283169309569",
      "bot": [
        "6285385198675"
      ],
      "token": "jagpro_kuex4yzjnh784o6p",
      "limit": 1
    },
    {
      "user": "6285829658816",
      "bot": [
        "573159874343"
      ],
      "token": "jagpro_yob5alsfffyt41hs",
      "limit": 1
    },
    {
      "user": "6282372514618",
      "bot": [
        "6285218952441"
      ],
      "token": "jagpro_vjyivyjd4dhnt9p6",
      "limit": 1
    },
    {
      "user": "6285837816643",
      "bot": [],
      "token": "jagpro_vkscpcuc24zty7ow",
      "limit": 1
    }
  ]
}